wagtailtranslations/__init__.py
wagtailtranslations/edit_handlers.py
wagtailtranslations/fields.py
wagtailtranslations/forms.py
wagtailtranslations/models.py
wagtailtranslations/version.py
wagtailtranslations/wagtail_hooks.py
wagtailtranslations/migrations/0001_initial.py
wagtailtranslations/migrations/__init__.py
wagtailtranslations/templates/wagtailtranslations/admin/page_listing_button.html
wagtailtranslations-2.0.1.dist-info/LICENSE
wagtailtranslations-2.0.1.dist-info/METADATA
wagtailtranslations-2.0.1.dist-info/WHEEL
wagtailtranslations-2.0.1.dist-info/top_level.txt
wagtailtranslations-2.0.1.dist-info/RECORD
