Metadata-Version: 2.1
Name: wagtailtranslations
Version: 2.0.1
Summary: Page translation plugin for Wagtail
Home-page: https://github.com/neon-jungle/wagtail-translations/
Author: Neon Jungle
Author-email: developers@neonjungle.studio
License: BSD License
Platform: UNKNOWN
Classifier: Environment :: Web Environment
Classifier: Intended Audience :: Developers
Classifier: Operating System :: OS Independent
Classifier: Programming Language :: Python
Classifier: Framework :: Django
Classifier: License :: OSI Approved :: BSD License
Requires-Dist: wagtail (>=2.0)
Requires-Dist: wagtailfontawesome (~=1.0)
